indian_cities/__init__.py
indian_cities/dj_city.py
indian_cities-1.0.1.dist-info/LICENSE
indian_cities-1.0.1.dist-info/METADATA
indian_cities-1.0.1.dist-info/WHEEL
indian_cities-1.0.1.dist-info/top_level.txt
indian_cities-1.0.1.dist-info/RECORD
