Metadata-Version: 2.1
Name: indian_cities
Version: 1.0.1
Summary: Django Indian Cities
Home-page: https://github.com/chayandatta/django_indian_cities
Author: Chayan Datta
Author-email: chayan.datta1996@gmail.com
License: MIT
Classifier: Programming Language :: Python :: 3
Classifier: License :: OSI Approved :: MIT License
Classifier: Operating System :: OS Independent
Requires-Python: >=3.0
License-File: LICENSE
